taoverse/__init__.py
taoverse/metagraph/__init__.py
taoverse/metagraph/metagraph_syncer.py
taoverse/metagraph/miner_iterator.py
taoverse/metagraph/utils.py
taoverse/model/__init__.py
taoverse/model/auto.py
taoverse/model/data.py
taoverse/model/model_tracker.py
taoverse/model/model_updater.py
taoverse/model/pretrained.py
taoverse/model/utils.py
taoverse/model/competition/__init__.py
taoverse/model/competition/competition_tracker.py
taoverse/model/competition/data.py
taoverse/model/competition/epsilon.py
taoverse/model/competition/utils.py
taoverse/model/eval/__init__.py
taoverse/model/eval/normalization.py
taoverse/model/eval/task.py
taoverse/model/storage/__init__.py
taoverse/model/storage/local_model_store.py
taoverse/model/storage/model_metadata_store.py
taoverse/model/storage/remote_model_store.py
taoverse/model/storage/chain/__init__.py
taoverse/model/storage/chain/chain_model_metadata_store.py
taoverse/model/storage/disk/__init__.py
taoverse/model/storage/disk/disk_model_store.py
taoverse/model/storage/disk/utils.py
taoverse/model/storage/hugging_face/__init__.py
taoverse/model/storage/hugging_face/hugging_face_model_store.py
taoverse/model/tts/auto.py
taoverse/model/tts/e2tts.py
taoverse/model/tts/backbones/cfm.py
taoverse/model/tts/backbones/unett.py
taoverse/model/tts/modules/e2tts.py
taoverse/model/tts/modules/f5tts.py
taoverse/model/tts/utils/e2tts.py
taoverse/utilities/__init__.py
taoverse/utilities/enum_action.py
taoverse/utilities/logging.py
taoverse/utilities/perf_monitor.py
taoverse/utilities/utils.py
taoverse/utilities/wandb.py
taoverse-2.0.2.dist-info/METADATA
taoverse-2.0.2.dist-info/WHEEL
taoverse-2.0.2.dist-info/licenses/LICENSE
taoverse-2.0.2.dist-info/RECORD
