Metadata-Version: 2.4
Name: taoverse
Version: 2.0.2
Summary: A utilities library for model training subnets.
Project-URL: Homepage, https://github.com/macrocosm-os/taoverse
Project-URL: Issues, https://github.com/macrocosm-os/taoverse/issues
Author: Taoverse
License-File: LICENSE
Classifier: Intended Audience :: Developers
Classifier: License :: OSI Approved :: MIT License
Classifier: Operating System :: OS Independent
Classifier: Programming Language :: Python :: 3 :: Only
Classifier: Programming Language :: Python :: 3.9
Classifier: Programming Language :: Python :: 3.10
Classifier: Topic :: Scientific/Engineering
Classifier: Topic :: Scientific/Engineering :: Artificial Intelligence
Classifier: Topic :: Software Development
Classifier: Topic :: Software Development :: Libraries
Classifier: Topic :: Software Development :: Libraries :: Python Modules
Requires-Python: >=3.9
Requires-Dist: bittensor==9.0.0
Requires-Dist: colorama
Requires-Dist: huggingface-hub
Requires-Dist: jieba==0.42.1
Requires-Dist: librosa==0.10.2.post1
Requires-Dist: numpy
Requires-Dist: pypinyin==0.53.0
Requires-Dist: safetensors
Requires-Dist: torch
Requires-Dist: torchdiffeq==0.2.5
Requires-Dist: transformers
Requires-Dist: wandb
Requires-Dist: x-transformers==2.1.5
